{"v":"5.7.1","ip":0,"op":240,"nm":"Composition","mn":"{e509d512-6662-4057-8abc-bd3fab907e6e}","fr":60,"w":480,"h":480,"assets":[],"layers":[{"ddd":0,"ty":4,"ind":1,"st":0,"ip":0,"op":241,"nm":"","mn":"{94dbfb3d-e54c-48d0-b449-0e11ee2f6918}","ao":0,"ks":{"a":{"a":0,"k":[6.250,3.950]},"p":{"a":1,"k":[{"t":5,"s":[240,300],"h":0,"o":{"x":[0.084],"y":[0.084]},"i":{"x":[0.667],"y":[1]},"to":[0,0],"ti":[0,0]},{"t":21,"s":[240,222],"h":0,"o":{"x":[0.084],"y":[0.084]},"i":{"x":[0.916],"y":[0.916]},"to":[0,0],"ti":[0,0]},{"t":22,"s":[240,300]}]},"s":{"a":0,"k":[1,1]},"r":{"a":0,"k":0},"o":{"a":1,"k":[{"t":5,"s":[100],"h":0,"o":{"x":[0.167],"y":[0.167]},"i":{"x":[0.833],"y":[0.833]}},{"t":21,"s":[0],"h":0,"o":{"x":[0.167],"y":[0.167]},"i":{"x":[0.833],"y":[0.833]}},{"t":31,"s":[0],"h":0,"o":{"x":[0.167],"y":[0.167]},"i":{"x":[0.833],"y":[0.833]}},{"t":50,"s":[100]}]}},"shapes":[{"ty":"gr","nm":"Group","mn":"{08e6cdab-53df-4890-a3d7-7313a84cc947}","it":[{"ty":"sh","nm":"Path","mn":"{ec9e67f2-ca33-42ca-b7c2-be753efc0b12}","d":1,"ks":{"a":0,"k":{"c":true,"v":[[-4.600,3.700],[-6,2.300],[0,-3.700],[6,2.300],[4.600,3.700],[0,-0.900]],"i":[[0,0],[0,0],[0,0],[0,0],[0,0],[0,0]],"o":[[0,0],[0,0],[0,0],[0,0],[0,0],[0,0]]}}},{"ty":"fl","nm":"Fill","mn":"{20450bc7-5484-475e-bb9f-ad5e494c31d5}","o":{"a":0,"k":100},"r":1,"c":{"a":0,"k":[0.910,0.918,0.929]}},{"ty":"tr","a":{"a":0,"k":[0,0]},"p":{"a":0,"k":[6.250,3.950]},"s":{"a":0,"k":[1.750e+05,1.750e+05]},"r":{"a":0,"k":0},"o":{"a":0,"k":100}}]}]},{"ddd":0,"ty":4,"ind":0,"st":0,"ip":0,"op":241,"nm":"","mn":"{71e1daa2-f57d-472c-9255-dd3bd2bcc063}","ao":0,"ks":{"a":{"a":0,"k":[6.250,3.950]},"p":{"a":1,"k":[{"t":0,"s":[240,180],"h":0,"o":{"x":[0.084],"y":[0.084]},"i":{"x":[0.667],"y":[1]},"to":[0,0],"ti":[0,0]},{"t":21,"s":[240,102],"h":0,"o":{"x":[0.084],"y":[0.084]},"i":{"x":[0.916],"y":[0.916]},"to":[0,0],"ti":[0,0]},{"t":22,"s":[240,180]}]},"s":{"a":0,"k":[1,1]},"r":{"a":0,"k":0},"o":{"a":1,"k":[{"t":0,"s":[100],"h":0,"o":{"x":[0.167],"y":[0.167]},"i":{"x":[0.833],"y":[0.833]}},{"t":21,"s":[0],"h":0,"o":{"x":[0.167],"y":[0.167]},"i":{"x":[0.833],"y":[0.833]}},{"t":31,"s":[0],"h":0,"o":{"x":[0.167],"y":[0.167]},"i":{"x":[0.833],"y":[0.833]}},{"t":51,"s":[100]}]}},"shapes":[{"ty":"gr","nm":"Group 1","mn":"{66c142ff-7f40-42c5-b46d-f5bba6a9aa05}","it":[{"ty":"sh","nm":"Path 1","mn":"{60a82d8f-73cf-49f3-baf7-b54b708d7533}","d":1,"ks":{"a":0,"k":{"c":true,"v":[[-4.600,3.700],[-6,2.300],[0,-3.700],[6,2.300],[4.600,3.700],[0,-0.900]],"i":[[0,0],[0,0],[0,0],[0,0],[0,0],[0,0]],"o":[[0,0],[0,0],[0,0],[0,0],[0,0],[0,0]]}}},{"ty":"fl","nm":"Fill 1","mn":"{7a342bb3-0371-4f5f-94f9-6ce067e5465c}","o":{"a":0,"k":100},"r":1,"c":{"a":0,"k":[0.910,0.918,0.929]}},{"ty":"tr","a":{"a":0,"k":[0,0]},"p":{"a":0,"k":[6.250,3.950]},"s":{"a":0,"k":[1.750e+05,1.750e+05]},"r":{"a":0,"k":0},"o":{"a":0,"k":100}}]}]}],"meta":{"g":"Glaxnimate 0.5.4"}}